hl7parser/__init__.py
hl7parser/hl7.py
hl7parser/hl7_data_types.py
hl7parser/hl7_segments.py
tests/__init__.py
tests/data_types.py
tests/test_hl7.py
tests/test_parse.py
hl7parser-0.7.5.dist-info/LICENSE
hl7parser-0.7.5.dist-info/METADATA
hl7parser-0.7.5.dist-info/WHEEL
hl7parser-0.7.5.dist-info/top_level.txt
hl7parser-0.7.5.dist-info/zip-safe
hl7parser-0.7.5.dist-info/RECORD
