Metadata-Version: 2.1
Name: hl7parser
Version: 0.7.5
Summary: A simple HL7 parser
Home-page: https://github.com/mps-gmbh/hl7-parser
Author: Medizinische Planungssysteme GmbH
Author-email: development@mps-med.de
License: BSD
Keywords: hl7,Health Level 7,parser,medical record
Classifier: Development Status :: 5 - Production/Stable
Classifier: Intended Audience :: Developers
Classifier: License :: OSI Approved :: BSD License
Classifier: Topic :: Communications
Classifier: Topic :: Scientific/Engineering :: Medical Science Apps.
Classifier: Programming Language :: Python :: 3
License-File: LICENSE
